galaxy/error/__init__.py
galaxy/error/app.py
galaxy/error/cmd.py
galaxy/error/code.py
galaxy/error/constant.py
galaxy/error/db.py
galaxy/error/error.py
galaxy/error/io.py
galaxy/error/net.py
galaxy/error/service.py
galaxy/error/sys.py
galaxy_py_error-0.0.2.dist-info/AUTHORS
galaxy_py_error-0.0.2.dist-info/COPYING.md
galaxy_py_error-0.0.2.dist-info/LICENSE.txt
galaxy_py_error-0.0.2.dist-info/METADATA
galaxy_py_error-0.0.2.dist-info/WHEEL
galaxy_py_error-0.0.2.dist-info/RECORD
