Metadata-Version: 2.3
Name: galaxy-py-error
Version: 0.0.2
Summary: Python Error for the Galaxy Project
License: Apache-2.0
Keywords: galaxy,galaxy-error
Author: Bastien Saltel
Author-email: bastien.saltel@gmail.com
Maintainer: Bastien Saltel
Maintainer-email: bastien.saltel@gmail.com
Requires-Python: >=3.10
Classifier: Development Status :: 3 - Alpha
Classifier: Programming Language :: Python :: 3
Classifier: Operating System :: OS Independent
Requires-Dist: galaxy-py-utils
Project-URL: Changelog, https://github.com/bsaltel/galaxy-py-error/blob/main/CHANGELOG.md
Project-URL: Documentation, https://github.com/bsaltel/galaxy-py-error
Project-URL: Homepage, https://github.com/bsaltel/galaxy-py-error
Project-URL: Issues, https://github.com/bsaltel/galaxy-py-error/issues
Project-URL: Repository, https://github.com/bsaltel/galaxy-py-error.git
